Metadata-Version: 1.1
Name: language
Version: 0.1
Summary: Basic tools for working with natural language text data
Home-page: https://github.com/signaln/language
Author: Signal N
Author-email: language@signaln.com
License: UNKNOWN
Download-URL: https://github.com/signaln/language/archive/0.1.tar.gz
Keywords: natural language processing,text,language,ngrams
Platform: UNKNOWN
